influxhtm/__init__.py
influxhtm/htmmodelresults.py
influxhtm/htmsensormodel.py
influxhtm/influxhtmclient.py
influxhtm/sensor.py
influxhtm/version.py
influxhtm-0.0.3.dist-info/DESCRIPTION.rst
influxhtm-0.0.3.dist-info/METADATA
influxhtm-0.0.3.dist-info/metadata.json
influxhtm-0.0.3.dist-info/RECORD
influxhtm-0.0.3.dist-info/top_level.txt
influxhtm-0.0.3.dist-info/WHEEL
