Metadata-Version: 2.0
Name: influxhtm
Version: 0.0.3
Summary: InfluxDB interface for use with HTM systems.
Home-page: UNKNOWN
Author: UNKNOWN
Author-email: UNKNOWN
License: UNKNOWN
Platform: UNKNOWN
Requires-Dist: influxdb (==2.12.0)
Requires-Dist: python-dateutil (==2.5.0)
Requires-Dist: pytz (==2015.7)
Requires-Dist: requests (==2.9.1)
Requires-Dist: six (==1.10.0)
Requires-Dist: wsgiref (==0.1.2)
